almanacbot/__init__.py
almanacbot/almanacbot.py
almanacbot/config.py
almanacbot/constants.py
almanacbot/data_loader.py
almanacbot/epehemeris_sample.json
almanacbot/ephemeris.py
almanacbot/postgresql_client.py
almanacbot/twitter_client.py
almanac_bot-1.1.3.dist-info/METADATA
almanac_bot-1.1.3.dist-info/WHEEL
almanac_bot-1.1.3.dist-info/licenses/LICENSE.txt
almanac_bot-1.1.3.dist-info/RECORD
