Metadata-Version: 2.4
Name: almanac-bot
Version: 1.1.3
Summary: Almanac bot for Twitter.
Project-URL: homepage, https://github.com/logoff/almanac-bot
Project-URL: repository, https://github.com/logoff/almanac-bot
Project-URL: documentation, https://github.com/logoff/almanac-bot
Project-URL: Bug Tracker, https://github.com/logoff/almanac-bot/issues
Author: logoff
License-Expression: MIT
License-File: LICENSE.txt
Keywords: history,twitter
Classifier: Topic :: Software Development :: Build Tools
Classifier: Topic :: Software Development :: Libraries :: Python Modules
Requires-Python: <3.14,>=3.13
Requires-Dist: babel<3,>=2.17.0
Requires-Dist: psycopg[binary]<4,>=3.2.4
Requires-Dist: sqlalchemy<3,>=2.0.38
Requires-Dist: tweepy<5,>=4.15.0
Requires-Dist: typer<0.16,>=0.15.1
